roadtools/roadtx/__init__.py
roadtools/roadtx/federation.py
roadtools/roadtx/firstpartyscopes.json
roadtools/roadtx/keepass.py
roadtools/roadtx/main.py
roadtools/roadtx/selenium.py
roadtools/roadtx/utils.py
roadtx-1.21.1.dist-info/METADATA
roadtx-1.21.1.dist-info/WHEEL
roadtx-1.21.1.dist-info/entry_points.txt
roadtx-1.21.1.dist-info/top_level.txt
roadtx-1.21.1.dist-info/RECORD
