Metadata-Version: 2.4
Name: roadtx
Version: 1.21.1
Summary: ROADtools Token eXchange
Home-page: https://github.com/dirkjanm/ROADtools/
Author: Dirk-jan Mollema
Author-email: dirkjan@outsidersecurity.nl
License: MIT
Classifier: Intended Audience :: Information Technology
Classifier: Programming Language :: Python :: 3
Classifier: Programming Language :: Python :: 3.9
Classifier: Programming Language :: Python :: 3.10
Classifier: Programming Language :: Python :: 3.11
Classifier: Programming Language :: Python :: 3.12
Classifier: Programming Language :: Python :: 3.13
Requires-Dist: roadlib>=1.6
Requires-Dist: requests
Requires-Dist: selenium
Requires-Dist: selenium-wire-roadtx
Requires-Dist: pyotp
Requires-Dist: pycryptodomex
Requires-Dist: signxml>3
Requires-Dist: setuptools
Dynamic: author
Dynamic: author-email
Dynamic: classifier
Dynamic: home-page
Dynamic: license
Dynamic: requires-dist
Dynamic: summary
